{
  "signedContributors": [
    {
      "name": "Samikshaaggarwal",
      "id": 123529409,
      "comment_id": 4609301800,
      "created_at": "2026-06-03T05:16:29Z",
      "repoId": 1144342210,
      "pullRequestNo": 34
    },
    {
      "name": "Dineshkumar2006471",
      "id": 190373696,
      "comment_id": 4610331441,
      "created_at": "2026-06-03T08:09:54Z",
      "repoId": 1144342210,
      "pullRequestNo": 35
    },
    {
      "name": "ramitbuilds",
      "id": 162986164,
      "comment_id": 4610602955,
      "created_at": "2026-06-03T08:47:44Z",
      "repoId": 1144342210,
      "pullRequestNo": 40
    },
    {
      "name": "NirmalMishra08",
      "id": 145590866,
      "comment_id": 4612620738,
      "created_at": "2026-06-03T13:07:02Z",
      "repoId": 1144342210,
      "pullRequestNo": 41
    },
    {
      "name": "prachishelke1312",
      "id": 228935308,
      "comment_id": 4614742783,
      "created_at": "2026-06-03T16:49:23Z",
      "repoId": 1144342210,
      "pullRequestNo": 42
    },
    {
      "name": "Excalibur677",
      "id": 186459520,
      "comment_id": 4616884647,
      "created_at": "2026-06-03T21:30:44Z",
      "repoId": 1144342210,
      "pullRequestNo": 43
    },
    {
      "name": "Rohit4507",
      "id": 173172758,
      "comment_id": 4701815515,
      "created_at": "2026-06-14T12:57:37Z",
      "repoId": 1144342210,
      "pullRequestNo": 96
    },
    {
      "name": "ManthanSiroya",
      "id": 237607330,
      "comment_id": 4702394642,
      "created_at": "2026-06-14T16:43:43Z",
      "repoId": 1144342210,
      "pullRequestNo": 98
    },
    {
      "name": "Rudra-clrscr",
      "id": 184661908,
      "comment_id": 4702810342,
      "created_at": "2026-06-14T19:29:05Z",
      "repoId": 1144342210,
      "pullRequestNo": 103
    },
    {
      "name": "AshutoshDash1999",
      "id": 46455250,
      "comment_id": 4710838349,
      "created_at": "2026-06-15T18:00:21Z",
      "repoId": 1144342210,
      "pullRequestNo": 106
    },
    {
      "name": "404akshat",
      "id": 254877304,
      "comment_id": 4712437129,
      "created_at": "2026-06-15T21:06:03Z",
      "repoId": 1144342210,
      "pullRequestNo": 109
    },
    {
      "name": "the-madhankumar",
      "id": 123907939,
      "comment_id": 4720600021,
      "created_at": "2026-06-16T15:43:26Z",
      "repoId": 1144342210,
      "pullRequestNo": 114
    },
    {
      "name": "Gunjan10-droid",
      "id": 142145209,
      "comment_id": 4721527908,
      "created_at": "2026-06-16T17:35:12Z",
      "repoId": 1144342210,
      "pullRequestNo": 107
    },
    {
      "name": "pavsoss",
      "id": 230380953,
      "comment_id": 4721985213,
      "created_at": "2026-06-16T18:24:01Z",
      "repoId": 1144342210,
      "pullRequestNo": 116
    },
    {
      "name": "Aharshi3614",
      "id": 158016093,
      "comment_id": 4725222950,
      "created_at": "2026-06-17T02:00:54Z",
      "repoId": 1144342210,
      "pullRequestNo": 112
    },
    {
      "name": "MEHWISH310",
      "id": 197863310,
      "comment_id": 4727159493,
      "created_at": "2026-06-17T07:22:49Z",
      "repoId": 1144342210,
      "pullRequestNo": 117
    }
  ]
}